<?xml version="1.0" encoding="utf-8" ?>
<Defs>

  <ThingDef Name="BasedWeapon" ParentName="BasedMom" Abstract="True">
    <designationCategory>Rimatomics</designationCategory>
    <tickerType>Normal</tickerType>
    <castEdgeShadows>false</castEdgeShadows>
    <blockWind>true</blockWind>
    <altitudeLayer>Building</altitudeLayer>
    <passability>PassThroughOnly</passability>
    <pathCost>150</pathCost>
    <terrainAffordanceNeeded>Light</terrainAffordanceNeeded>
    <constructEffect>ConstructMetal</constructEffect>
    <hasTooltip>true</hasTooltip>
    <staticSunShadowHeight>0</staticSunShadowHeight>
    <canOverlapZones>false</canOverlapZones>
  </ThingDef>

  <ThingDef ParentName="BasedWeapon">
    <defName>PPC</defName>
    <label>Pulsed Power Capacitor</label>
    <description>A PPC stores large amounts of energy, which can be discharged in a single pulse by energy weapons</description>
    <thingClass>Rimatomics.Building_PPC</thingClass>
    <graphicData>
      <texPath>Things/RimatomicsBuildings/PPC</texPath>
      <graphicClass>Graphic_Multi</graphicClass>
      <drawSize>(3,5)</drawSize>
    </graphicData>
    <size>(2,4)</size>
    <fillPercent>0.60</fillPercent>
    <statBases>
      <MaxHitPoints>200</MaxHitPoints>
      <WorkToBuild>800</WorkToBuild>
      <Mass>2000</Mass>
      <Flammability>1.0</Flammability>
      <Beauty>-18</Beauty>
    </statBases>
    <building>
      <ai_combatDangerous>true</ai_combatDangerous>
    </building>
    <costList>
      <Steel>400</Steel>
      <Component>8</Component>
    </costList>
    <comps>
      <li Class="CompProperties_Battery">
        <storedEnergyMax>6000</storedEnergyMax>
        <efficiency>0.9</efficiency>
        <startElectricalFires>false</startElectricalFires>
        <transmitsPower>true</transmitsPower>
      </li>
      <li Class="CompProperties_Breakdownable"/>
    </comps>
    <rimatomicsPrerequisites>
      <li>EnergyWeapons6</li>
    </rimatomicsPrerequisites>
    <constructionSkillPrerequisite>5</constructionSkillPrerequisite>
  </ThingDef>

  <ThingDef ParentName="BasedWeapon">
    <defName>PPCWeaponsConsole</defName>
    <label>Weapons Console</label>
    <description>A manned target acquisition computer required by all energy weapons</description>
    <thingClass>Rimatomics.WeaponsConsole</thingClass>
    <graphicData>
      <texPath>Things/RimatomicsBuildings/WarRoom</texPath>
      <graphicClass>Graphic_Multi</graphicClass>
      <shaderType>CutoutComplex</shaderType>
      <drawSize>(6,3)</drawSize>
    </graphicData>
    <drawGUIOverlay>True</drawGUIOverlay>
    <fillPercent>1</fillPercent>
    <size>(5,2)</size>
    <statBases>
      <MaxHitPoints>250</MaxHitPoints>
      <WorkToBuild>9800</WorkToBuild>
      <Flammability>1.0</Flammability>
    </statBases>
    <hasInteractionCell>True</hasInteractionCell>
    <interactionCellOffset>(0,0,-1)</interactionCellOffset>
    <rotatable>true</rotatable>
    <costList>
      <Steel>250</Steel>
      <Component>6</Component>
    </costList>
    <comps>
      <li Class="CompProperties_Mannable">
        <manWorkType>Violent</manWorkType>
      </li>
      <li Class="CompProperties_Power">
        <compClass>CompPowerTrader</compClass>
        <basePowerConsumption>175</basePowerConsumption>
        <startElectricalFires>true</startElectricalFires>
      </li>
      <li Class="CompProperties_Flickable"/>
      <li Class="CompProperties_Breakdownable"/>
    </comps>
    <building>
      <ai_combatDangerous>true</ai_combatDangerous>
    </building>
    <rimatomicsPrerequisites>
      <li>EnergyWeapons4</li>
      <li>ICBM3</li>
    </rimatomicsPrerequisites>
    <constructionSkillPrerequisite>5</constructionSkillPrerequisite>
  </ThingDef>

  <ThingDef ParentName="BasedWeapon">
    <defName>RadarDish</defName>
    <label>TACS</label>
    <description>The Target Acquisition and Communication System uses a combination of technologies to track land and air based targets and communicate with weapon systems.</description>
    <thingClass>Rimatomics.Building_Radar</thingClass>
    <graphicData>
      <texPath>Things/RimatomicsBuildings/WeaponBase</texPath>
      <graphicClass>Graphic_Single</graphicClass>
      <drawSize>(3,3)</drawSize>
    </graphicData>
    <uiIconPath>UI/Radar</uiIconPath>
    <rotatable>false</rotatable>
    <statBases>
      <MaxHitPoints>180</MaxHitPoints>
      <Flammability>1.0</Flammability>
      <WorkToBuild>2500</WorkToBuild>
      <Mass>100</Mass>
      <Beauty>-60</Beauty>
    </statBases>
    <comps>
      <li Class="CompProperties_Power">
        <compClass>CompPowerTrader</compClass>
        <basePowerConsumption>550</basePowerConsumption>
      </li>
      <li Class="CompProperties_Flickable"/>
      <li Class="CompProperties_Breakdownable"/>
    </comps>
    <size>(3,3)</size>
    <fillPercent>0.8</fillPercent>
    <costList>
      <Steel>275</Steel>
      <Component>6</Component>
    </costList>
    <terrainAffordanceNeeded>Light</terrainAffordanceNeeded>
    <building>
      <turretTopGraphicPath>Things/RimatomicsBuildings/RadarDish</turretTopGraphicPath>
    </building>
    <designationHotKey>Misc2</designationHotKey>
    <placeWorkers>
      <li>PlaceWorker_NotUnderRoof</li>
      <li>Rimatomics.PlaceWorker_ResearchStage</li>
    </placeWorkers>
    <rimatomicsPrerequisites>
      <li>EnergyWeapons5</li>
      <li>ICBM4</li>
    </rimatomicsPrerequisites>
    <constructionSkillPrerequisite>5</constructionSkillPrerequisite>
  </ThingDef>

  <ThingDef ParentName="BasedWeapon">
    <defName>PPCADS</defName>
    <label>ADS</label>
    <description>The ADS (Active Denial System) is a directed energy weapon that uses microwaves to burn groups of enemies forcing them to flee, Requires a weapons console and a PPC for power.</description>
    <thingClass>Rimatomics.Building_ADS</thingClass>
    <graphicData>
      <texPath>Things/RimatomicsBuildings/WeaponBase</texPath>
      <graphicClass>Graphic_Single</graphicClass>
      <drawSize>(3,3)</drawSize>
    </graphicData>
    <uiIconPath>UI/ADS</uiIconPath>
    <rotatable>false</rotatable>
    <statBases>
      <MaxHitPoints>300</MaxHitPoints>
      <Flammability>1.0</Flammability>
      <WorkToBuild>2500</WorkToBuild>
      <Mass>100</Mass>
      <Beauty>-60</Beauty>
    </statBases>
    <comps>
      <li Class="CompProperties_Power">
        <compClass>CompPowerTrader</compClass>
        <basePowerConsumption>200</basePowerConsumption>
      </li>
      <li Class="CompProperties_Flickable"/>
      <li Class="CompProperties_Breakdownable"/>
      <li Class="Rimatomics.CompProperties_Upgradable">
        <upgrades>
          <li>
            <project>ResearchMEPS</project>
            <stats>
              <li>Area of effect +10</li>
              <li>Range +10</li>
              <li>Power +50%</li>
            </stats>
          </li>
          <li>
            <project>ResearchALC</project>
            <stats>
              <li>Cooldown -1s</li>
            </stats>
          </li>
          <li>
            <project>ResearchERS</project>
            <stats>
              <li>Power -50%</li>
            </stats>
          </li>
          <li>
            <project>ResearchDriveActuator</project>
          </li>
        </upgrades>
      </li>
    </comps>
    <size>(3,3)</size>
    <fillPercent>0.4</fillPercent>
    <costList>
      <Steel>600</Steel>
      <Component>5</Component>
    </costList>
    <terrainAffordanceNeeded>Light</terrainAffordanceNeeded>
    <specialDisplayRadius>24</specialDisplayRadius>
    <building>
      <ai_combatDangerous>true</ai_combatDangerous>
      <turretTopGraphicPath>Things/RimatomicsBuildings/ADSdish</turretTopGraphicPath>
    </building>
    <designationHotKey>Misc2</designationHotKey>
    <placeWorkers>
      <li>Rimatomics.PlaceWorker_ResearchStage</li>
    </placeWorkers>
    <rimatomicsPrerequisites>
      <li>ADS3</li>
    </rimatomicsPrerequisites>
    <constructionSkillPrerequisite>5</constructionSkillPrerequisite>
  </ThingDef>

  <ThingDef ParentName="BasedWeapon">
    <defName>PPCTeslaCoil</defName>
    <label>Tesla Coil</label>
    <description>Delivers a large electrical discharge to anything within range. Short range. Requires a weapons console and a PPC for power.</description>
    <thingClass>Rimatomics.Building_TeslaCoil</thingClass>
    <graphicData>
      <texPath>Things/RimatomicsBuildings/teslaCoil</texPath>
      <graphicClass>Graphic_Single</graphicClass>
      <drawSize>(4,4)</drawSize>
    </graphicData>
    <size>(3,3)</size>
    <fillPercent>0.4</fillPercent>
    <rotatable>false</rotatable>
    <statBases>
      <MaxHitPoints>250</MaxHitPoints>
      <Flammability>1.0</Flammability>
      <WorkToBuild>2500</WorkToBuild>
      <Mass>100</Mass>
      <Beauty>-60</Beauty>
    </statBases>
    <comps>
      <li Class="CompProperties_Power">
        <compClass>CompPowerTrader</compClass>
        <basePowerConsumption>75</basePowerConsumption>
      </li>
      <li Class="CompProperties_Flickable"/>
      <li Class="CompProperties_Breakdownable"/>
      <li Class="Rimatomics.CompProperties_Upgradable">
        <upgrades>
          <li>
            <project>ResearchMEPS</project>
            <stats>
              <li>Damage +15</li>
              <li>Range +10</li>
              <li>Power +50%</li>
            </stats>
          </li>
          <li>
            <project>ResearchALC</project>
            <stats>
              <li>Cooldown -10s</li>
            </stats>
          </li>
          <li>
            <project>ResearchERS</project>
            <stats>
              <li>Power -50%</li>
            </stats>
          </li>
        </upgrades>
      </li>
    </comps>
    <costList>
      <Steel>175</Steel>
      <Component>3</Component>
    </costList>
    <specialDisplayRadius>14.9</specialDisplayRadius>
    <building>
      <ai_combatDangerous>true</ai_combatDangerous>
    </building>
    <designationHotKey>Misc2</designationHotKey>
    <drawOffscreen>true</drawOffscreen>
    <placeWorkers>
      <li>Rimatomics.PlaceWorker_ResearchStage</li>
    </placeWorkers>
    <rimatomicsPrerequisites>
      <li>TeslaCoil3</li>
    </rimatomicsPrerequisites>
    <constructionSkillPrerequisite>6</constructionSkillPrerequisite>
  </ThingDef>



  <ThingDef ParentName="BasedWeapon">
    <defName>PPCHEL</defName>
    <label>HEL</label>
    <description>The HEL (High Energy Laser) is a weapon that uses a laser to destroy incoming airborne projectiles. Requires a weapons console and a PPC for power.</description>
    <thingClass>Rimatomics.Building_HEL</thingClass>
    <graphicData>
      <texPath>Things/RimatomicsBuildings/WeaponBase</texPath>
      <graphicClass>Graphic_Single</graphicClass>
      <drawSize>(4,4)</drawSize>
    </graphicData>
    <uiIconPath>UI/HEL</uiIconPath>
    <drawOffscreen>true</drawOffscreen>
    <rotatable>false</rotatable>
    <size>(4,4)</size>
    <fillPercent>0.4</fillPercent>
    <specialDisplayRadius>55</specialDisplayRadius>
    <comps>
      <li Class="CompProperties_Power">
        <compClass>CompPowerTrader</compClass>
        <basePowerConsumption>250</basePowerConsumption>
      </li>
      <li Class="CompProperties_Flickable"/>
      <li Class="CompProperties_Breakdownable"/>
      <li Class="Rimatomics.CompProperties_Upgradable">
        <upgrades>
          <li>
            <project>ResearchMEPS</project>
            <stats>
              <li>Shootdown time -50%</li>
              <li>Cooldown +2.5s</li>
              <li>Power +50%</li>
            </stats>
          </li>
          <li>
            <project>ResearchALC</project>
            <stats>
              <li>Cooldown -2.5s</li>
            </stats>
          </li>
          <li>
            <project>ResearchERS</project>
            <stats>
              <li>Power -50%</li>
            </stats>
          </li>
          <li>
            <project>ResearchDriveActuator</project>
          </li>
        </upgrades>
      </li>
    </comps>
    <statBases>
      <MaxHitPoints>200</MaxHitPoints>
      <Flammability>1.0</Flammability>
      <WorkToBuild>2700</WorkToBuild>
      <Mass>200</Mass>
      <Beauty>-60</Beauty>
    </statBases>
    <building>
      <ai_combatDangerous>true</ai_combatDangerous>
      <turretTopGraphicPath>Things/RimatomicsBuildings/LaWStop</turretTopGraphicPath>
    </building>
    <placeWorkers>
      <li>PlaceWorker_NotUnderRoof</li>
      <li>Rimatomics.PlaceWorker_ResearchStage</li>
    </placeWorkers>
    <costList>
      <Steel>650</Steel>
      <Component>8</Component>
    </costList>
    <designationHotKey>Misc3</designationHotKey>
    <rimatomicsPrerequisites>
      <li>HEL3</li>
    </rimatomicsPrerequisites>
    <constructionSkillPrerequisite>12</constructionSkillPrerequisite>

  </ThingDef>




  <ThingDef Name="BaseRailgunBuilding" ParentName="BasedWeapon" Abstract="True">
    <altitudeLayer>Building</altitudeLayer>
    <stealable>false</stealable>
    <size>(4,4)</size>
    <passability>PassThroughOnly</passability>
    <pathCost>50</pathCost>
    <fillPercent>0.4</fillPercent>
    <castEdgeShadows>true</castEdgeShadows>
    <tickerType>Normal</tickerType>
    <specialDisplayRadius>55</specialDisplayRadius>
    <terrainAffordanceNeeded>Light</terrainAffordanceNeeded>
    <inspectorTabs>
      <li>Rimatomics.ITab_ShellsRailgun</li>
    </inspectorTabs>
    <comps>
      <li Class="CompProperties_Power">
        <compClass>CompPowerTrader</compClass>
        <basePowerConsumption>350</basePowerConsumption>
      </li>
      <li Class="CompProperties_Flickable"/>
      <li Class="CompProperties_Breakdownable"/>
      <li Class="Rimatomics.CompProperties_Upgradable">
        <upgrades>
          <li>
            <project>ResearchMEPS</project>
            <stats>
              <li>Cooldown +5s</li>
              <li>Range +10 Tiles</li>
            </stats>
          </li>
          <li>
            <project>ResearchALC</project>
            <stats>
              <li>Cooldown -10s</li>
            </stats>
          </li>
          <li>
            <project>ResearchERS</project>
            <stats>
              <li>Power -25%</li>
            </stats>
          </li>
          <li>
            <project>ResearchRailgun_TargetingChip</project>
          </li>
          <li>
            <project>ResearchDriveActuator</project>
          </li>
        </upgrades>
      </li>
    </comps>
    <statBases>
      <MaxHitPoints>480</MaxHitPoints>
      <Flammability>1.0</Flammability>
      <WorkToBuild>2900</WorkToBuild>
      <Mass>100</Mass>
      <Beauty>-20</Beauty>
    </statBases>
    <building>
      <turretBurstWarmupTime>4.0</turretBurstWarmupTime>
      <turretBurstCooldownTime>28.0</turretBurstCooldownTime>
    </building>
    <placeWorkers>
      <li>PlaceWorker_NotUnderRoof</li>
      <li>Rimatomics.PlaceWorker_ResearchStage</li>
    </placeWorkers>
    <costList>
      <Steel>650</Steel>
      <Component>10</Component>
    </costList>
    <uiIconPath>UI/Railgun</uiIconPath>
    <rimatomicsPrerequisites>
      <li>Railgun3</li>
    </rimatomicsPrerequisites>
    <constructionSkillPrerequisite>15</constructionSkillPrerequisite>
  </ThingDef>

  <ThingDef Name="BaseRailgunWeapon" Abstract="True">
    <category>Item</category>
    <thingClass>ThingWithComps</thingClass>
    <label>artillery error</label>
    <useHitPoints>false</useHitPoints>
    <equipmentType>Primary</equipmentType>
    <tickerType>Never</tickerType>
    <techLevel>Industrial</techLevel>
    <destroyOnDrop>True</destroyOnDrop>
    <rotatable>false</rotatable>
    <canBeSpawningInventory>false</canBeSpawningInventory>
    <menuHidden>True</menuHidden>
    <tradeability>Never</tradeability>
    <comps>
      <li>
        <compClass>CompEquippable</compClass>
      </li>
      <li Class="CompProperties_ChangeableProjectile" />
    </comps>
    <building>
      <fixedStorageSettings>
        <filter>
          <categories>
            <li>SabotRounds</li>
          </categories>
        </filter>
      </fixedStorageSettings>
      <defaultStorageSettings>
        <filter>
          <categories>
            <li>SabotRounds</li>
          </categories>
        </filter>
      </defaultStorageSettings>
    </building>
  </ThingDef>




  <ThingDef ParentName="BaseRailgunBuilding">
    <defName>PPCRailgun</defName>
    <label>Railgun</label>
    <description>A weapon that uses a large electromagnetic pulse to launch a projectile to extreme ranges. Requires a weapons console and a PPC for power.</description>
    <thingClass>Rimatomics.Building_Railgun</thingClass>
    <graphicData>
      <texPath>Things/RimatomicsBuildings/WeaponBase</texPath>
      <graphicClass>Graphic_Single</graphicClass>
      <drawSize>(4,4)</drawSize>
      <damageData>
        <rect>(0.38,0.2,0.56375,0.8)</rect>
        <cornerTL>Damage/Corner</cornerTL>
      </damageData>
    </graphicData>
    <designationHotKey>Misc3</designationHotKey>
    <building>
      <turretGunDef>Railgun_Cannon</turretGunDef>
      <turretTopGraphicPath>Things/RimatomicsBuildings/Railgun_Top</turretTopGraphicPath>
    </building>
  </ThingDef>

  <ThingDef ParentName="BaseRailgunWeapon">
    <defName>Railgun_Cannon</defName>
    <label>mortar</label>
    <description>Mortar launcher. Lobs bombs over walls. Very inaccurate but long-ranged.</description>
    <weaponTags>
      <li>TurretGun</li>
    </weaponTags>
    <verbs>
      <li>
        <verbClass>Verb_Shoot</verbClass>
        <forceNormalTimeSpeed>false</forceNormalTimeSpeed>
        <hasStandardCommand>true</hasStandardCommand>
        <warmupTime>5.8</warmupTime>
        <forcedMissRadius>6</forcedMissRadius>
        <requireLineOfSight>false</requireLineOfSight>
        <minRange>55</minRange>
        <range>500</range>
        <burstShotCount>1</burstShotCount>
        <soundCast>railgunDischarge</soundCast>
        <muzzleFlashScale>24</muzzleFlashScale>
        <targetParams>
          <canTargetLocations>true</canTargetLocations>
        </targetParams>
      </li>
    </verbs>
  </ThingDef>







  <ThingDef ParentName="BasedWeapon">
    <defName>PPCObelisk</defName>
    <label>Obelisk</label>
    <description>A directed energy weapon that uses a focused laser to burn targets. Highly accurate with long range, Requires a weapons console and a PPC for power.</description>
    <thingClass>Rimatomics.Building_Obelisk</thingClass>
    <graphicData>
      <texPath>Things/RimatomicsBuildings/obelisk</texPath>
      <graphicClass>Graphic_Multi</graphicClass>
      <drawSize>(5,5)</drawSize>
    </graphicData>
    <size>(3,3)</size>
    <fillPercent>0.4</fillPercent>
    <drawOffscreen>true</drawOffscreen>
    <rotatable>true</rotatable>
    <statBases>
      <MaxHitPoints>420</MaxHitPoints>
      <Flammability>1.0</Flammability>
      <WorkToBuild>2500</WorkToBuild>
      <Mass>100</Mass>
      <Beauty>-60</Beauty>
    </statBases>
    <comps>
      <li Class="CompProperties_Power">
        <compClass>CompPowerTrader</compClass>
        <basePowerConsumption>350</basePowerConsumption>
      </li>
      <li Class="CompProperties_Flickable"/>
      <li Class="CompProperties_Breakdownable"/>
      <li Class="Rimatomics.CompProperties_Upgradable">
        <upgrades>
          <li>
            <project>ResearchMEPS</project>
            <stats>
              <li>Damage +50%</li>
              <li>Power +50%</li>
            </stats>
          </li>
          <li>
            <project>ResearchALC</project>
            <stats>
              <li>Cooldown -10s</li>
            </stats>
          </li>
          <li>
            <project>ResearchERS</project>
            <stats>
              <li>Power -50%</li>
            </stats>
          </li>
          <li>
            <project>ResearchObelisk_LenseModule</project>
          </li>
          <li>
            <project>ResearchObelisk_BeamSplitter</project>
          </li>
        </upgrades>
      </li>
    </comps>
    <costStuffCount>75</costStuffCount>
    <costList>
      <Steel>600</Steel>
      <Component>12</Component>
    </costList>
    <specialDisplayRadius>40</specialDisplayRadius>
    <building>
      <ai_combatDangerous>true</ai_combatDangerous>
    </building>
    <designationHotKey>Misc2</designationHotKey>
    <placeWorkers>
      <li>Rimatomics.PlaceWorker_ResearchStage</li>
    </placeWorkers>
    <rimatomicsPrerequisites>
      <li>Obelisk3</li>
    </rimatomicsPrerequisites>
    <constructionSkillPrerequisite>18</constructionSkillPrerequisite>
  </ThingDef>

  <!-- ICBM -->

  <ThingDef ParentName="BasedWeapon">
    <defName>MissileSilo</defName>
    <label>Missile Silo</label>
    <thingClass>Rimatomics.MissileSilo</thingClass>
    <fillPercent>0.2</fillPercent>
    <description>A launch pad is an above-ground platform from which a rocket-powered missile is vertically launched.</description>
    <graphicData>
      <texPath>Things/RimatomicsBuildings/silo</texPath>
      <graphicClass>Graphic_Single</graphicClass>
      <drawSize>(9,5)</drawSize>
    </graphicData>
    <category>Building</category>
    <passability>Standable</passability>
    <surfaceType>Item</surfaceType>
    <altitudeLayer>Building</altitudeLayer>
    <rotatable>false</rotatable>
    <tickerType>Normal</tickerType>
    <selectable>true</selectable>
    <size>(9,5)</size>
    <castEdgeShadows>true</castEdgeShadows>
    <blockWind>false</blockWind>
    <constructEffect>ConstructMetal</constructEffect>
    <staticSunShadowHeight>0.2</staticSunShadowHeight>
    <drawOffscreen>true</drawOffscreen>
    <costList>
      <Steel>750</Steel>
      <Component>15</Component>
    </costList>
    <statBases>
      <MaxHitPoints>900</MaxHitPoints>
      <WorkToBuild>10000</WorkToBuild>
      <Flammability>0</Flammability>
      <Beauty>-30</Beauty>
    </statBases>
    <comps>
      <li Class="CompProperties_Power">
        <compClass>CompPowerTrader</compClass>
        <basePowerConsumption>2000</basePowerConsumption>
      </li>
      <li Class="CompProperties_Flickable"/>
      <li Class="CompProperties_Breakdownable"/>
    </comps>
    <placeWorkers>
      <li>PlaceWorker_NotUnderRoof</li>
    </placeWorkers>
    <drawPlaceWorkersWhileSelected>true</drawPlaceWorkersWhileSelected>
    <rimatomicsPrerequisites>
      <li>ICBM3</li>
    </rimatomicsPrerequisites>
    <constructionSkillPrerequisite>16</constructionSkillPrerequisite>
  </ThingDef>

  <ThingDef>
    <defName>notReal</defName>
    <label>notReal</label>
    <thingClass>Rimatomics.notReal</thingClass>
    <category>Item</category>
    <tickerType>Normal</tickerType>
    <graphicData>
      <texPath>Things/Untitled</texPath>
      <graphicClass>Graphic_Single</graphicClass>
      <drawSize>(6,6)</drawSize>
    </graphicData>
    <altitudeLayer>MapDataOverlay</altitudeLayer>
    <useHitPoints>false</useHitPoints>
    <drawOffscreen>true</drawOffscreen>
    <passability>Impassable</passability>
  </ThingDef>

</Defs>